poe_client/__init__.py
poe_client/client.py
poe_client/client_test.py
poe_client/py.typed
poe_client/rate_limiter.py
poe_client/schemas/__init__.py
poe_client/schemas/account.py
poe_client/schemas/character.py
poe_client/schemas/filter.py
poe_client/schemas/league.py
poe_client/schemas/pvp.py
poe_client/schemas/stash.py
poe_client-0.5.1.dist-info/LICENSE
poe_client-0.5.1.dist-info/WHEEL
poe_client-0.5.1.dist-info/METADATA
poe_client-0.5.1.dist-info/RECORD
