Metadata-Version: 2.1
Name: poe-client
Version: 0.5.1
Summary: Async PoE API client with rate limit support (upcoming)
Home-page: https://github.com/BPL-Development-Team/poe-client
License: MIT
Keywords: poe,pathofexile,aiohttp,async,pydantic,mypy
Author: bittermandel
Requires-Python: >=3.6.2,<4.0.0
Classifier: Development Status :: 3 - Alpha
Classifier: Intended Audience :: Developers
Classifier: License :: OSI Approved :: MIT License
Classifier: Operating System :: OS Independent
Classifier: Programming Language :: Python :: 3
Classifier: Programming Language :: Python :: 3.10
Classifier: Programming Language :: Python :: 3.7
Classifier: Programming Language :: Python :: 3.8
Classifier: Programming Language :: Python :: 3.9
Classifier: Topic :: Software Development :: Libraries :: Python Modules
Requires-Dist: aiohttp (>=3.7.4,<4.0.0)
Requires-Dist: black (>=21.12b0,<22.0)
Requires-Dist: pydantic (>=1.8.2,<2.0.0)
Requires-Dist: pyhumps (>=3.0.2,<4.0.0)
Requires-Dist: pytest-asyncio (>=0.15.1,<0.16.0)
Project-URL: Repository, https://github.com/BPL-Development-Team/poe-client
